basewebapi/__init__.py
basewebapi/basewebapi.py
basewebapi/json_objects.py
basewebapi/asyncbasewebapi/__init__.py
basewebapi/asyncbasewebapi/abasewebapi.py
basewebapi-0.4.5.dist-info/LICENSE
basewebapi-0.4.5.dist-info/METADATA
basewebapi-0.4.5.dist-info/WHEEL
basewebapi-0.4.5.dist-info/top_level.txt
basewebapi-0.4.5.dist-info/RECORD
