Metadata-Version: 2.1
Name: basewebapi
Version: 0.4.5
Summary: A python module defining a basic object orientated framework that can be inherited by custom modules that interact with HTTP based RESTful APIs.
Home-page: https://github.com/djnrrd/basewebapi
Author: DJ Nrrd
Author-email: djnrrd@gmail.com
License: UNKNOWN
Project-URL: Bug Tracker, https://github.com/djnrrd/basewebapi/issues
Platform: UNKNOWN
Classifier: License :: OSI Approved :: GNU General Public License v3 (GPLv3)
Classifier: Development Status :: 5 - Production/Stable
Classifier: Environment :: Console
Classifier: Topic :: Software Development :: Libraries :: Python Modules
Requires-Python: >=3.6
License-File: LICENSE
Requires-Dist: requests
Requires-Dist: aiohttp
